{
    "people": [
        {
            "person": "Bluetouff",
            "books": [
                {
                    "title": "Le Prince",
                    "author": "Nicolas Machiavel",
                    "link_amazon_book": "https://amzn.to/3vqLtpq",
                    "image": "https://m.media-amazon.com/images/I/71rymI-m0mL._SY522_.jpg"
                },
                {
                    "title": "Le rêve d'un homme ridicule",
                    "author": "Fiodor Mikhaïlovitch Dostoïevski",
                    "link_amazon_book": "",
                    "image": ""
                }
            ]
        },
        {
            "person": "Fabrice Epelboin",
            "books": [
                {
                    "title": "L'homme révolté",
                    "author": "Albert Camus",
                    "link_amazon_book": "https://amzn.to/3H9x9Et",
                    "image": "https://m.media-amazon.com/images/I/81mGlfigybL._SY522_.jpg"
                }
            ]
        }
    ]
}